plezmo_ble_driver_py/__init__.py
plezmo_ble_driver_py/ble_adapter.py
plezmo_ble_driver_py/ble_driver.py
plezmo_ble_driver_py/ble_driver_types.py
plezmo_ble_driver_py/config.py
plezmo_ble_driver_py/exceptions.py
plezmo_ble_driver_py/observers.py
plezmo_ble_driver_py/examples/__init__.py
plezmo_ble_driver_py/examples/advertising.py
plezmo_ble_driver_py/examples/heart_rate_collector.py
plezmo_ble_driver_py/examples/serial_port_enum.py
plezmo_ble_driver_py/hex/__init__.py
plezmo_ble_driver_py/hex/sd_api_v2/__init__.py
plezmo_ble_driver_py/hex/sd_api_v2/connectivity_4.1.1_1m_with_s130_2.0.1.hex
plezmo_ble_driver_py/hex/sd_api_v2/connectivity_4.1.1_1m_with_s132_2.0.0.hex
plezmo_ble_driver_py/hex/sd_api_v2/s130_nrf51_2.0.1_softdevice.hex
plezmo_ble_driver_py/hex/sd_api_v5/__init__.py
plezmo_ble_driver_py/lib/__init__.py
plezmo_ble_driver_py/lib/_nrf_ble_driver_sd_api_v2.pyd
plezmo_ble_driver_py/lib/_nrf_ble_driver_sd_api_v6.pyd
plezmo_ble_driver_py/lib/nrf-ble-driver-sd_api_v2-mt-4_0_0.dll
plezmo_ble_driver_py/lib/nrf-ble-driver-sd_api_v6-mt-4_0_0.dll
plezmo_ble_driver_py/lib/nrf_ble_driver_sd_api_v2.lib
plezmo_ble_driver_py/lib/nrf_ble_driver_sd_api_v2.py
plezmo_ble_driver_py/lib/nrf_ble_driver_sd_api_v6.lib
plezmo_ble_driver_py/lib/nrf_ble_driver_sd_api_v6.py
tests/__init__.py
tests/ble_driver_test.py
tests/test_ble_common_api.py
tests/test_driver_open_close.py
tests/test_pc_ble_driver_py.py
tests/test_programming.py
tests/test_rssi.py
plezmo_ble_driver_py-0.12.2.dist-info/LICENSE
plezmo_ble_driver_py-0.12.2.dist-info/METADATA
plezmo_ble_driver_py-0.12.2.dist-info/WHEEL
plezmo_ble_driver_py-0.12.2.dist-info/top_level.txt
plezmo_ble_driver_py-0.12.2.dist-info/RECORD
