Metadata-Version: 2.1
Name: plezmo-ble-driver-py
Version: 0.12.2
Summary: Python bindings for the Nordic pc-ble-driver SoftDevice serialization library
Home-page: UNKNOWN
Author: Nordic Semiconductor ASA
License: Modified BSD License
Keywords: nordic nrf51 nrf52 ble bluetooth softdevice serialization bindings pc-ble-driver pc-ble-driver-py pc_ble_driver plezmo_ble_driver_py
Platform: UNKNOWN
Classifier: Development Status :: 4 - Beta
Classifier: Intended Audience :: Developers
Classifier: Operating System :: MacOS
Classifier: Operating System :: Microsoft :: Windows
Classifier: Operating System :: POSIX :: Linux
Classifier: Topic :: System :: Networking
Classifier: Topic :: System :: Hardware :: Hardware Drivers
Classifier: Topic :: Software Development :: Embedded Systems
Classifier: License :: Other/Proprietary License
Classifier: Programming Language :: Python
Classifier: Programming Language :: Python :: 2
Classifier: Programming Language :: Python :: 2.7
Classifier: Programming Language :: Python :: 3
Classifier: Programming Language :: Python :: 3.7
Requires-Python: >=2.7, !=3.0.*, !=3.1.*, !=3.2.*, !=3.3.*, !=3.4.*, !=3.5.*, !=3.6.*, <4
Requires-Dist: wrapt
Requires-Dist: future
